f2ap/__init__.py
f2ap/__main__.py
f2ap/activitypub.py
f2ap/config.py
f2ap/data.py
f2ap/feed.py
f2ap/json.py
f2ap/markdown.py
f2ap/model.py
f2ap/postie.py
f2ap/signature.py
f2ap/webserver.py
f2ap-0.1.0.dist-info/entry_points.txt
f2ap-0.1.0.dist-info/LICENSE.md
f2ap-0.1.0.dist-info/METADATA
f2ap-0.1.0.dist-info/WHEEL
f2ap-0.1.0.dist-info/RECORD
