Metadata-Version: 2.1
Name: f2ap
Version: 0.1.0
Summary: Put your website on the Fediverse thanks to your RSS/Atom feed
Home-page: https://github.com/Deuchnord/f2ap
License: AGPL-3.0-or-later
Keywords: f2ap,activitypub,blog,rss,atom
Author: Jérôme Deuchnord
Author-email: jerome@deuchnord.fr
Requires-Python: >=3.9,<4.0
Classifier: Development Status :: 3 - Alpha
Classifier: Framework :: FastAPI
Classifier: License :: OSI Approved :: GNU Affero General Public License v3 or later (AGPLv3+)
Classifier: Programming Language :: Python :: 3
Classifier: Programming Language :: Python :: 3.9
Classifier: Programming Language :: Python :: 3.10
Classifier: Programming Language :: Python :: 3.11
Classifier: Topic :: Communications
Classifier: Topic :: Internet :: WWW/HTTP
Requires-Dist: fastapi (>=0.88.0,<0.89.0)
Requires-Dist: feedparser (>=6.0,<7.0)
Requires-Dist: markdown (>=3.4.1,<4.0.0)
Requires-Dist: mdx-linkify (>=2.1,<3.0)
Requires-Dist: pycryptodome (>=3.16.0,<4.0.0)
Requires-Dist: pydantic (>=1.10.2,<2.0.0)
Requires-Dist: pyhumps (>=3.8.0,<4.0.0)
Requires-Dist: requests (>=2.28.1,<3.0.0)
Requires-Dist: toml (>=0.10.2,<0.11.0)
Requires-Dist: uvicorn[standard] (>=0.20.0,<0.21.0)
Project-URL: Repository, https://github.com/Deuchnord/f2ap
